tokenizer_adapter/__init__.py
tokenizer_adapter/adapter.py
tokenizer_adapter-0.2.0.dist-info/LICENSE
tokenizer_adapter-0.2.0.dist-info/METADATA
tokenizer_adapter-0.2.0.dist-info/WHEEL
tokenizer_adapter-0.2.0.dist-info/top_level.txt
tokenizer_adapter-0.2.0.dist-info/RECORD
