Metadata-Version: 2.1
Name: tokenizer-adapter
Version: 0.2.0
Summary: A simple to adapt a pretrained language model to a new vocabulary
Home-page: https://github.com/ccdv-ai/tokenizer-adapter
Author: Charles Condevaux
Author-email: charles.condevaux@gmail.com
Classifier: Programming Language :: Python :: 3
Classifier: License :: OSI Approved :: MIT License
Classifier: Operating System :: OS Independent
Requires-Python: >=3.8
License-File: LICENSE
Requires-Dist: torch >=1.8
Requires-Dist: tokenizers >=0.15.0
Requires-Dist: tqdm
